parseable_connector/__init__.py
parseable_connector/parseable_dialect.py
sqlalchemy_parseable-0.1.6.dist-info/LICENSE
sqlalchemy_parseable-0.1.6.dist-info/METADATA
sqlalchemy_parseable-0.1.6.dist-info/WHEEL
sqlalchemy_parseable-0.1.6.dist-info/entry_points.txt
sqlalchemy_parseable-0.1.6.dist-info/top_level.txt
sqlalchemy_parseable-0.1.6.dist-info/RECORD
